{"cameraMode":{"drawMode":0,"name":"Shaded","section":"Shading Mode"},"sceneLighting":false,"audioPlay":false,"sceneViewState":{"m_AlwaysRefresh":false,"showFog":true,"showSkybox":false,"showFlares":true,"showImageEffects":true,"showParticleSystems":true,"showVisualEffectGraphs":true,"m_FxEnabled":true},"in2DMode":false,"pivot":{"x":0.0,"y":2.264145612716675,"z":0.0},"rotation":{"x":0.23032794892787934,"y":0.026270072907209398,"z":-0.006220731884241104,"w":0.9727439284324646},"size":7.384474277496338,"orthographic":false}